{"stats":{"total":23,"passed":23},"status":"passed","newTests":[{"id":"d19075bacecfa854574512e89fb47a20","name":"Bot should ignore not supporting messages","status":"passed","duration":3},{"id":"5811f7386fef99f625d873642926b498","name":"Bot should react on clicking button 'Anima Stone'","status":"passed","duration":1221},{"id":"3f76ac66acb6611bd5c09d4c14b44b65","name":"Bot should react on clicking button options in 'skills' menu","status":"passed","duration":12},{"id":"3bd16d4908731256b324683b36ff3d1a","name":"Bot should react on clicking button 'settings'","status":"passed","duration":7},{"id":"b4f1357a3dffddce3e112b71d233c2be","name":"Bot should send message about selecting next command","status":"passed","duration":26},{"id":"61b5eb7c1dac0283608ae692477e2852","name":"testServiceGetRateMethod","status":"passed","duration":2664},{"id":"c5dd7c835f8b1550b2430e6c6f049832","name":"Bot should send message with Settings","status":"passed","duration":5},{"id":"0bad611d27d99de5c807e355ed1c19f3","name":"Bot should react on clicking button options in 'skills' menu","status":"passed","duration":8},{"id":"751eb6d7175038ea4dfd6f0612988fc9","name":"Bot should react on clicking button 'settings'","status":"passed","duration":9},{"id":"92b8035d0747d2f123ea8344aafb4224","name":"testServiceAnalyzeSkillsMethod","status":"passed","duration":2085},{"id":"53d87a5a5a9cb170db1e16a1513de1f7","name":"Bot should react on clicking button 'Divination Recipes'","status":"passed","duration":14},{"id":"2d86a907c554a518ff60aef69e4ecdeb","name":"Bot should ignore not supporting interaction","status":"passed","duration":13},{"id":"03f7d8be9161462d375e8ebe8ad1617a","name":"testServiceGetSkillsMethod","status":"passed","duration":21},{"id":"6d05307c58e419be2be8f5a5aa052485","name":"Bot should react on clicking button 'settings'","status":"passed","duration":8},{"id":"720f67a5639c3b9a90bf1d8f614bc744","name":"Bot should react on clicking button 'settings'","status":"passed","duration":9},{"id":"dd312cc01a6b34b5bbf2dc4dd37d1978","name":"Bot should welcome user when he writes command '/start'","status":"passed","duration":224},{"id":"cceb88cefc3cb2fd8f456194848de18f","name":"Bot should react on clicking button options in 'skills' menu","status":"passed","duration":10},{"id":"723dda2e1aed706bec72bb7678ee832e","name":"Bot should react on clicking button 'Vendor Recipes'","status":"passed","duration":12091},{"id":"49077d812639ca617e5643e048e7571b","name":"Bot should react on clicking button 'settings'","status":"passed","duration":6},{"id":"7374b9c03ff1961bb78ae535f439a67e","name":"Bot should react on clicking button 'settings'","status":"passed","duration":6},{"id":"fedc475c1b6fcaa9d66fdf8f95df315c","name":"Spring service 'A8r' should be healthy","status":"passed","duration":4372},{"id":"9fbfaaad080635b2b97a5e7a2a85d96d","name":"testServiceGetUniqueJewelMethod","status":"passed","duration":3},{"id":"d6088dbc5d8b58072f822104a8fa1884","name":"Bot should react on clicking button options in 'skills' menu","status":"passed","duration":120}],"flakyTests":[],"retryTests":[],"name":"Allure Report","duration":22937,"createdAt":1778867349674,"plugin":"Awesome","meta":{"reportId":"39cd2ca1-d1ec-4700-aeb3-f1e194939cf1","singleFile":false,"withTestResultsLinks":true},"pluginId":"awesome","pullRequestHref":"","jobHref":"https://github.com/ylazakovich/path-of-exile-starter/actions/runs/25932557657"}