{"stats":{"total":23,"passed":23},"status":"passed","newTests":[{"id":"59ed355982df3b4734839d04669ebd1f","name":"Bot should welcome user when he writes command '/start'","status":"passed","duration":273},{"id":"b4c728ec4442f44691714f54eb5e07d9","name":"Bot should react on clicking button 'settings'","status":"passed","duration":7},{"id":"3af135dc5bce8b655a73ebddf16bff3a","name":"Bot should react on clicking button 'settings'","status":"passed","duration":7},{"id":"340ac9f559c1aa353d53e1bb8ab4a9d5","name":"Bot should send message about selecting next command","status":"passed","duration":25},{"id":"a54d22aaa025d9b4dc7f13c5aaec90d7","name":"Bot should react on clicking button 'settings'","status":"passed","duration":9},{"id":"bf8413920fc58af4fb17e194af82c5f9","name":"testServiceAnalyzeSkillsMethod","status":"passed","duration":1940},{"id":"db8d5cc8e6edcdc3267a1dbc43fa11eb","name":"Bot should send message with Settings","status":"passed","duration":4},{"id":"01488d06bd20f2afcfd7bbb033b1e569","name":"testServiceGetRateMethod","status":"passed","duration":2843},{"id":"d8e28eb659481c0877a4316789f3ee39","name":"Bot should react on clicking button options in 'skills' menu","status":"passed","duration":115},{"id":"fc77e48b90630d74d1aba7e6f78f9ece","name":"Bot should ignore not supporting messages","status":"passed","duration":7},{"id":"cf64f257c4eb6e0c20744be5fc5fbda2","name":"Bot should react on clicking button 'settings'","status":"passed","duration":8},{"id":"3e9d553869f18b2bc3c97f25bf2afd2d","name":"Bot should react on clicking button 'settings'","status":"passed","duration":8},{"id":"b3d27d890887fc5fffdc31b8ec877213","name":"Bot should react on clicking button 'Divination Recipes'","status":"passed","duration":15},{"id":"0612ded9e52858c17f9c623f3e1abdcf","name":"Bot should ignore not supporting interaction","status":"passed","duration":13},{"id":"6c925610c30260ed6a38c0ce18299272","name":"Bot should react on clicking button 'settings'","status":"passed","duration":8},{"id":"3fe1e9581e0548b4043dee84762bc311","name":"Bot should react on clicking button 'Anima Stone'","status":"passed","duration":1400},{"id":"b48cfc796df97b7cc41e7437b3a3ceca","name":"testServiceGetUniqueJewelMethod","status":"passed","duration":3},{"id":"b7a02a97d21c9c4b691d56d080926f71","name":"testServiceGetSkillsMethod","status":"passed","duration":20},{"id":"b0064a2a8953e4f95d4854ebbe320a03","name":"Bot should react on clicking button options in 'skills' menu","status":"passed","duration":8},{"id":"75bc5b437631a96c5b8fb2d3d84a80f0","name":"Spring service 'A8r' should be healthy","status":"passed","duration":3699},{"id":"e958471200779d6e773ad7db6821e66a","name":"Bot should react on clicking button options in 'skills' menu","status":"passed","duration":8},{"id":"0b6f0d628147eccb816ffc03af36a6c5","name":"Bot should react on clicking button 'Vendor Recipes'","status":"passed","duration":16602},{"id":"37229a95e4d87abd458b90897d812746","name":"Bot should react on clicking button options in 'skills' menu","status":"passed","duration":8}],"flakyTests":[],"retryTests":[],"name":"Allure Report – Pull request #1040","duration":27030,"createdAt":1780841498467,"plugin":"Awesome","meta":{"reportId":"7be1d034-0055-4a80-a590-04795ec18a17","singleFile":false,"withTestResultsLinks":true},"pluginId":"awesome","pullRequestHref":"https://github.com/ylazakovich/path-of-exile-starter/pull/1040","jobHref":"https://github.com/ylazakovich/path-of-exile-starter/actions/runs/27094815230","href":"awesome/"}